cschwabpy/SchwabAsyncClient.py
cschwabpy/SchwabClient.py
cschwabpy/costants.py
cschwabpy/models/__init__.py
cschwabpy/models/token.py
cschwabpy/models/trade_models.py
cschwabpy/util.py
cschwabpy-0.1.4.8.dist-info/METADATA
cschwabpy-0.1.4.8.dist-info/WHEEL
cschwabpy-0.1.4.8.dist-info/RECORD
